ozgursozluk/__init__.py
ozgursozluk/configs.py
ozgursozluk/main.py
ozgursozluk/views.py
ozgursozluk/static/favicon.png
ozgursozluk/static/fontello.css
ozgursozluk/static/manifest.json
ozgursozluk/static/robots.txt
ozgursozluk/static/style.css
ozgursozluk/static/font/fontello.eot
ozgursozluk/static/font/fontello.svg
ozgursozluk/static/font/fontello.ttf
ozgursozluk/static/font/fontello.woff
ozgursozluk/static/font/fontello.woff2
ozgursozluk/static/theme/black-metal.css
ozgursozluk/static/theme/dark.css
ozgursozluk/static/theme/discord.css
ozgursozluk/static/theme/gay-light.css
ozgursozluk/static/theme/gruvbox.css
ozgursozluk/static/theme/iceberg-dark.css
ozgursozluk/static/theme/light.css
ozgursozluk/static/theme/startpage.css
ozgursozluk/static/theme/violet.css
ozgursozluk/static/theme/yotsuba-b.css
ozgursozluk/templates/about.html
ozgursozluk/templates/author-badges.html
ozgursozluk/templates/author.html
ozgursozluk/templates/base.html
ozgursozluk/templates/debe.html
ozgursozluk/templates/entry.html
ozgursozluk/templates/index.html
ozgursozluk/templates/macros.html
ozgursozluk/templates/not-found.html
ozgursozluk/templates/paginate.html
ozgursozluk/templates/privacy-policy.html
ozgursozluk/templates/rss.xml
ozgursozluk/templates/search.html
ozgursozluk/templates/settings.html
ozgursozluk/templates/terms-of-service.html
ozgursozluk/templates/topic.html
ozgursozluk-0.9.6.dist-info/METADATA
ozgursozluk-0.9.6.dist-info/WHEEL
ozgursozluk-0.9.6.dist-info/licenses/LICENSE
ozgursozluk-0.9.6.dist-info/RECORD
