Metadata-Version: 2.4
Name: ozgursozluk
Version: 0.9.6
Dynamic: Description
Dynamic: Description-Content-Type
Summary: Free alternative Ekşi Sözlük front-end
Project-URL: Homepage, https://github.com/beucismis/ozgursozluk
Project-URL: Repository, https://github.com/beucismis/ozgursozluk
Project-URL: Changelog, https://github.com/beucismis/ozgursozluk/releases
Project-URL: Documentation, https://github.com/beucismis/ozgursozluk/blob/main/README.md
Author-email: beucismis <beucismis@tutamail.com>
License:             DO WHAT THE FUCK YOU WANT TO PUBLIC LICENSE
License-File: LICENSE
Classifier: Development Status :: 4 - Beta
Classifier: Framework :: Flask
Classifier: Programming Language :: Python
Classifier: Programming Language :: Python :: 3.8
Classifier: Programming Language :: Python :: 3.9
Classifier: Programming Language :: Python :: 3.10
Classifier: Programming Language :: Python :: 3.11
Classifier: Programming Language :: Python :: 3.12
Classifier: Programming Language :: Python :: Implementation :: CPython
Classifier: Programming Language :: Python :: Implementation :: PyPy
Classifier: Topic :: Internet
Requires-Python: >=3.8
Requires-Dist: flask==3.1.2
Requires-Dist: limoon
Provides-Extra: dev
Requires-Dist: black; extra == 'dev'
Requires-Dist: djlint; extra == 'dev'
